pymermaid2dir/__init__.py
pymermaid2dir/__main__.py
pymermaid2dir/fsnode.py
pymermaid2dir/graph.py
pymermaid2dir/vis.py
pymermaid2dir-1.0.0.dist-info/LICENSE
pymermaid2dir-1.0.0.dist-info/METADATA
pymermaid2dir-1.0.0.dist-info/WHEEL
pymermaid2dir-1.0.0.dist-info/top_level.txt
pymermaid2dir-1.0.0.dist-info/RECORD
