Metadata-Version: 2.1
Name: pymermaid2dir
Version: 1.0.0
Summary: Python module for simple reading of Excel(.xlsx)
Author-email: sonoh5n <hsono10n1@gmail.com>
Project-URL: Homepage, https://github.com/sonoh5n/pymermaid2dir
Project-URL: Bug Tracker, https://github.com/sonoh5n/pymermaid2dir/issues
Classifier: Programming Language :: Python :: 3
Classifier: License :: OSI Approved :: MIT License
Classifier: Operating System :: OS Independent
Requires-Python: >=3.8
License-File: LICENSE
